UpliftSegmentation/__init__.py
UpliftSegmentation/treatment_effect_learner.py
UpliftSegmentation/user_segmentor.py
UpliftSegmentation-0.2.1.dist-info/LICENSE.txt
UpliftSegmentation-0.2.1.dist-info/METADATA
UpliftSegmentation-0.2.1.dist-info/WHEEL
UpliftSegmentation-0.2.1.dist-info/top_level.txt
UpliftSegmentation-0.2.1.dist-info/RECORD
