Metadata-Version: 2.1
Name: UpliftSegmentation
Version: 0.2.1
Summary: This is a Python package designed for modeling and analyzing treatment effects to optimize user segmentation and uplift strategies.
Author: Eddie Baigabulov
Author-email: eddie.baigabulov@instacart.com
License-File: LICENSE.txt
Requires-Dist: numpy
Requires-Dist: pandas
Requires-Dist: scikit-learn
Requires-Dist: xgboost
Requires-Dist: matplotlib
